alleycat-0.5.0.dist-info/licenses/LICENSE
alleycat_apps/__init__.py
alleycat_apps/cli/__init__.py
alleycat_apps/cli/init_cmd.py
alleycat_apps/cli/main.py
alleycat_core/__init__.py
alleycat_core/logging.py
alleycat_core/config/__init__.py
alleycat_core/config/settings.py
alleycat_core/llm/__init__.py
alleycat_core/llm/base.py
alleycat_core/llm/evaluation.py
alleycat_core/llm/openai.py
alleycat_core/llm/py.typed
alleycat_core/llm/remote_file.py
alleycat_core/llm/types.py
alleycat_core/utils/__init__.py
alleycat-0.5.0.dist-info/METADATA
alleycat-0.5.0.dist-info/WHEEL
alleycat-0.5.0.dist-info/entry_points.txt
alleycat-0.5.0.dist-info/top_level.txt
alleycat-0.5.0.dist-info/RECORD
