Metadata-Version: 2.4
Name: alleycat
Version: 0.5.0
Summary: A command line tool for chat conversations with LLMs
Author-email: Andrew <andrew@groat.nz>
License: MIT
Project-URL: Homepage, https://github.com/avowkind/alleycat
Project-URL: Bug Tracker, https://github.com/avowkind/alleycat/issues
Project-URL: Documentation, https://github.com/avowkind/alleycat/tree/main/docs
Classifier: Development Status :: 4 - Beta
Classifier: Environment :: Console
Classifier: Intended Audience :: Developers
Classifier: Intended Audience :: End Users/Desktop
Classifier: License :: OSI Approved :: MIT License
Classifier: Programming Language :: Python :: 3
Classifier: Programming Language :: Python :: 3.12
Classifier: Topic :: Text Processing
Classifier: Topic :: Utilities
Requires-Python: >=3.12
License-File: LICENSE
Requires-Dist: openai>=1.12.0
Requires-Dist: typer>=0.9.0
Requires-Dist: rich>=13.7.0
Requires-Dist: pydantic>=2.6.1
Requires-Dist: pydantic-settings>=2.1.0
Requires-Dist: python-dotenv>=1.0.0
Requires-Dist: PyYAML>=6.0.1
Requires-Dist: platformdirs>=4.0.0
Provides-Extra: dev
Requires-Dist: pytest>=8.0.0; extra == "dev"
Requires-Dist: pytest-asyncio>=0.23.5; extra == "dev"
Requires-Dist: pytest-cov>=4.1.0; extra == "dev"
Requires-Dist: pytest-mock>=3.12.0; extra == "dev"
Requires-Dist: ruff>=0.2.1; extra == "dev"
Requires-Dist: mypy>=1.8.0; extra == "dev"
Requires-Dist: types-PyYAML>=6.0.12.12; extra == "dev"
Requires-Dist: build>=1.2.2.post1; extra == "dev"
Requires-Dist: twine>=6.1.0; extra == "dev"
Dynamic: license-file
